Metadata-Version: 2.1
Name: chungus
Version: 0.0.0
Summary: Chunky Module
Author: PyModuleDev
Author-email: pxcom@mail.com
Classifier: Development Status :: 5 - Production/Stable
Classifier: Intended Audience :: Developers
Classifier: Programming Language :: Python :: 3
Requires-Python: >=3.6
License-File: LICENSE
